shtwopy/__init__.py
shtwopy-0.1.0.dist-info/LICENSE
shtwopy-0.1.0.dist-info/METADATA
shtwopy-0.1.0.dist-info/WHEEL
shtwopy-0.1.0.dist-info/top_level.txt
shtwopy-0.1.0.dist-info/RECORD
