Metadata-Version: 2.1
Name: shtwopy
Version: 0.1.0
Summary: Convert a python script into a decrypted shell script and vice versa.
Author: Florian Grethler
License-File: LICENSE
